handshape_datasets/__init__.py
handshape_datasets/_config.py
handshape_datasets/_dataset_info.py
handshape_datasets/_dataset_loader.py
handshape_datasets/base.py
handshape_datasets-0.2.1.dist-info/METADATA
handshape_datasets-0.2.1.dist-info/WHEEL
handshape_datasets-0.2.1.dist-info/top_level.txt
handshape_datasets-0.2.1.dist-info/RECORD
