Metadata-Version: 2.1
Name: handshape-datasets
Version: 0.2.1
Summary: A single library to (down)load all existing sign language handshape datasets. This library allows you to automatically download and load various sign language handshape datasets. Currently supporting 13 different datasets.
Author-email: Facundo Manuel Quiroga <f{quiroga}@lidi.info.unlp.edu.ar>
Project-URL: Homepage, https://github.com/midusi/handshape_datasets
Project-URL: Documentation, https://github.com/midusi/handshape_datasets
Project-URL: Repository, https://github.com/midusi/handshape_datasets.git
Project-URL: Issues, https://github.com/midusi/handshape_datasets/issues
Project-URL: Changelog, https://github.com/midusi/handshape_datasets
Classifier: Topic :: Database
Classifier: Intended Audience :: Developers
Classifier: License :: OSI Approved :: GNU Affero General Public License v3 or later (AGPLv3+)
Classifier: Operating System :: OS Independent
Classifier: Programming Language :: Python :: 3.12
Classifier: Programming Language :: Python :: 3.13
Requires-Python: >=3.10
Requires-Dist: gdown>=5.2.0
Requires-Dist: hurry>=1.1
Requires-Dist: numpy>=2.2.0
Requires-Dist: opencv-python>=4.10.0.84
Requires-Dist: patool>=3.1.0
Requires-Dist: prettytable>=3.12.0
Requires-Dist: py7zr>=0.22.0
Requires-Dist: pyunpack>=0.3
Requires-Dist: requests>=2.32.3
Requires-Dist: scikit-image>=0.25.0
Requires-Dist: scipy>=1.14.1
Requires-Dist: xlsxwriter>=3.2.0
